qutip_qoc/__init__.py
qutip_qoc/_crab.py
qutip_qoc/_goat.py
qutip_qoc/_grape.py
qutip_qoc/_jopt.py
qutip_qoc/_optimizer.py
qutip_qoc/_rl.py
qutip_qoc/_time.py
qutip_qoc/objective.py
qutip_qoc/pulse.c
qutip_qoc/pulse.cp38-win_amd64.pyd
qutip_qoc/pulse.pyx
qutip_qoc/pulse_optim.py
qutip_qoc/result.py
qutip_qoc/version.py
qutip_qoc-0.1.1.dist-info/LICENSE
qutip_qoc-0.1.1.dist-info/METADATA
qutip_qoc-0.1.1.dist-info/WHEEL
qutip_qoc-0.1.1.dist-info/top_level.txt
qutip_qoc-0.1.1.dist-info/RECORD
