Metadata-Version: 2.1
Name: qutip-qoc
Version: 0.1.1
Summary: The QuTiP quantum optimal control package
Home-page: https://github.com/qutip/qutip-qoc
Author: Patrick Hopf, Paul Menczel, Alexander Pitchford, Neill Lambert
Author-email: qutip-admin@googlegroups.com
License: BSD 3-Clause License
Keywords: quantum,physics,dynamics
Platform: Linux
Platform: Mac OSX
Platform: Unix
Platform: Windows
Classifier: Development Status :: 4 - Beta
Classifier: Intended Audience :: Science/Research
Classifier: License :: OSI Approved :: BSD License
Classifier: Programming Language :: Python
Classifier: Programming Language :: Python :: 3
Classifier: Topic :: Scientific/Engineering
Classifier: Operating System :: MacOS
Classifier: Operating System :: POSIX
Classifier: Operating System :: Unix
Classifier: Operating System :: Microsoft :: Windows
License-File: LICENSE
Requires-Dist: jax
Requires-Dist: jaxlib
Requires-Dist: packaging
Requires-Dist: qutip
Requires-Dist: qutip-qtrl
Requires-Dist: qutip-jax
Requires-Dist: numpy (<2.0,>=1.16.6)
Requires-Dist: gymnasium (>=0.29.1)
Requires-Dist: stable-baselines3 (>=2.3.2)
Provides-Extra: full
Requires-Dist: pytest (>=6.0) ; extra == 'full'
Provides-Extra: tests
Requires-Dist: pytest (>=6.0) ; extra == 'tests'
